hosthome/__init__.py
hosthome/__main__.py
hosthome/comandos.py
hosthome/login.py
hosthome/version.py
HostHome_cli-1.0.2.dist-info/LICENSE.md
HostHome_cli-1.0.2.dist-info/METADATA
HostHome_cli-1.0.2.dist-info/WHEEL
HostHome_cli-1.0.2.dist-info/entry_points.txt
HostHome_cli-1.0.2.dist-info/top_level.txt
HostHome_cli-1.0.2.dist-info/RECORD
