Metadata-Version: 2.1
Name: HostHome-cli
Version: 1.0.2
Summary: HostHome-cli para empezar con el host
Home-page: https://github.com/HostHome-of/python-CLI
Author: Maubg
Author-email: UNKNOWN
License: GNU
Keywords: host,hosthome,maubg,python,py,hosty,hoster,home
Platform: UNKNOWN
Classifier: Development Status :: 3 - Alpha
Classifier: Environment :: Console
Classifier: Operating System :: Microsoft :: Windows
Classifier: Programming Language :: Python :: 2
Classifier: Programming Language :: Python :: 3
Requires-Dist: requests
Requires-Dist: warn
Requires-Dist: termcolor
Requires-Dist: docopt
